safelib/__init__.py
safelib/errors.py
safelib-0.6.1.dist-info/METADATA
safelib-0.6.1.dist-info/WHEEL
safelib-0.6.1.dist-info/top_level.txt
safelib-0.6.1.dist-info/RECORD
