Metadata-Version: 2.4
Name: safelib
Version: 0.6.1
Summary: An advanced library for safe importing and scoped imports management.
Home-page: https://github.com/fswair/safelib
Author: Mert Sirakaya
Maintainer: fswair
Maintainer-email: contact@tomris.dev
Classifier: Development Status :: 4 - Beta
Classifier: Intended Audience :: Developers
Classifier: License :: OSI Approved :: MIT License
Classifier: Programming Language :: Python :: 3.10
Classifier: Programming Language :: Python :: 3.11
Classifier: Programming Language :: Python :: 3.12
Classifier: Programming Language :: Python :: 3.13
Requires-Python: >=3.10
Dynamic: author
Dynamic: classifier
Dynamic: description
Dynamic: description-content-type
Dynamic: home-page
Dynamic: maintainer
Dynamic: maintainer-email
Dynamic: requires-python
Dynamic: summary
